bfas/__init__.py
bfas/bfas.py
bfas/archs/__init__.py
bfas/archs/arch_factory.py
bfas/env/Dockerfile
bfas/env/__init__.py
bfas/env/requirements.txt
bfas/tests/__init__.py
bfas/tests/test_archs.py
bfas/tests/test_utils.py
bfas/training/__init__.py
bfas/training/dataloader.py
bfas/training/trainer.py
bfas/utils/__init__.py
bfas/utils/complexity.py
bfas/utils/data_types.py
bfas/utils/fileio.py
bfas/utils/hardware.py
bfas/utils/logging.py
bfas/utils/vision.py
bfas-0.0.5.dist-info/LICENSE
bfas-0.0.5.dist-info/METADATA
bfas-0.0.5.dist-info/WHEEL
bfas-0.0.5.dist-info/top_level.txt
bfas-0.0.5.dist-info/RECORD
