Metadata-Version: 2.1
Name: bfas
Version: 0.0.5
Summary: Brute Force Architecture Search
Home-page: https://github.com/m-pektas/BFAS
Author: Muhammed Pektas
Keywords: bfas,efficient deep learning,NAS,neural architecture search,knowledge distillation
Requires-Python: >=3.7, <4
License-File: LICENSE
Requires-Dist: torchvision
Requires-Dist: thop
Requires-Dist: wandb
Requires-Dist: tensorboard
Requires-Dist: tqdm
Requires-Dist: py-cpuinfo
Requires-Dist: pytest
Requires-Dist: ptflops
